LICENSE
MANIFEST.in
README.md
setup.py
tox.ini
./docs/_static/.keepme
./docs/_templates/.keepme
bert/__init__.py
bert/__main__.py
bert/build.py
bert/display.py
bert/exc.py
bert/main.py
bert/yaml.py
bert/tasks/__init__.py
bert/tasks/add.py
bert/tasks/env.py
bert/tasks/export_deb.py
bert/tasks/export_file.py
bert/tasks/export_rpm.py
bert/tasks/export_tar.py
bert/tasks/fail.py
bert/tasks/fetch.py
bert/tasks/git.py
bert/tasks/import_tar.py
bert/tasks/include_vars.py
bert/tasks/patch.py
bert/tasks/read_file.py
bert/tasks/run.py
bert/tasks/script.py
bert/tasks/set_image_attr.py
bert/tasks/set_var.py
bert/utils/__init__.py
bert/utils/common.py
bert/utils/paths.py
bert/utils/targlob.py
bert_build.egg-info/PKG-INFO
bert_build.egg-info/SOURCES.txt
bert_build.egg-info/dependency_links.txt
bert_build.egg-info/entry_points.txt
bert_build.egg-info/requires.txt
bert_build.egg-info/top_level.txt
ci/build-dist.sh
ci/build-docs.sh
ci/publish-docs-s3.py
ci/run-tests.sh
docs/_tasks.rst
docs/build-files.rst
docs/conf.py
docs/index.rst
docs/make-tasks.py
docs/tasks.rst
docs/templating.rst
docs/usage/installation.rst
docs/usage/quickstart.rst
functests/README.rst
functests/capture.yml
functests/test_main.py
functests/tasks/add/absolute-dir.yml
functests/tasks/add/example.txt
functests/tasks/add/relative.yml
functests/tasks/env/env.yml
functests/tasks/export-file/export-glob.yml
functests/tasks/export-file/export.yml
functests/tasks/export-tar/hardlink-slash.yml
functests/tasks/export-tar/hardlink.yml
functests/tasks/export-tar/runnable.yml
functests/tasks/export-tar/single-dir-at.yml
functests/tasks/export-tar/single-dir-slash.yml
functests/tasks/export-tar/single-dir.yml
functests/tasks/export-tar/single-file-at.yml
functests/tasks/export-tar/single-file.yml
functests/tasks/import-tar/import-at.yml
functests/tasks/include-vars/_vars.yml
functests/tasks/include-vars/include.yml
functests/tasks/patch/patch-in-dir-p0.yml
functests/tasks/patch/patch-simple.yml
functests/tasks/patch/input/example.txt
functests/tasks/patch/input/subdir/example2.txt
functests/tasks/run/hello.yml
functests/tasks/script/contents.yml
functests/tasks/script/file.sh
functests/tasks/script/file.yml
