Metadata-Version: 2.1
Name: bert-build
Version: 0.0.1
Summary: Build things
Home-page: https://git.cornhooves.org/build-tools/bert
Author: Robin Schoonover
Author-email: robin@cornhooves.org
License: UNKNOWN
Platform: UNKNOWN
Classifier: Development Status :: 3 - Alpha
Classifier: Topic :: Software Development :: Build Tools
Classifier: Environment :: Console
Classifier: License :: OSI Approved :: MIT License
Classifier: Programming Language :: Python :: 3
Classifier: Programming Language :: Python :: 3.6
Classifier: Programming Language :: Python :: 3.7
Provides-Extra: docs
